gha_tools/__about__.py
gha_tools/__init__.py
gha_tools/__main__.py
gha_tools/action_updater.py
gha_tools/cli.py
gha_tools/github_api.py
gha_tools-0.2.0.dist-info/METADATA
gha_tools-0.2.0.dist-info/WHEEL
gha_tools-0.2.0.dist-info/entry_points.txt
gha_tools-0.2.0.dist-info/licenses/LICENSE.txt
gha_tools-0.2.0.dist-info/RECORD
