Metadata-Version: 2.4
Name: gha-tools
Version: 0.2.0
Project-URL: Documentation, https://github.com/akx/gha-tools#readme
Project-URL: Issues, https://github.com/akx/gha-tools/issues
Project-URL: Source, https://github.com/akx/gha-tools
Author-email: Aarni Koskela <akx@iki.fi>
License-Expression: MIT
License-File: LICENSE.txt
Classifier: Development Status :: 4 - Beta
Classifier: Programming Language :: Python
Classifier: Programming Language :: Python :: 3.10
Classifier: Programming Language :: Python :: 3.11
Classifier: Programming Language :: Python :: 3.12
Classifier: Programming Language :: Python :: 3.13
Classifier: Programming Language :: Python :: Implementation :: CPython
Classifier: Programming Language :: Python :: Implementation :: PyPy
Requires-Python: >=3.10
Requires-Dist: click>=7
